AnimeGameRemap/__init__.py
AnimeGameRemap/__main__.py
animegameremap-4.6.2.dist-info/licenses/LICENSE
animegameremap-4.6.2.dist-info/METADATA
animegameremap-4.6.2.dist-info/WHEEL
animegameremap-4.6.2.dist-info/top_level.txt
animegameremap-4.6.2.dist-info/RECORD
