Metadata-Version: 2.4
Name: AnimeGameRemap
Version: 4.6.2
Summary: A library to help remap the mods installed on a character onto the skins of the character
Author-email: NK <qqqqaaaapppp0000@gmail.com>, Albert Gold <AlexXianZhenYuAu@gmail.com>
Project-URL: Homepage, https://github.com/nhok0169/Anime-Game-Remap
Project-URL: Documentation, https://anime-game-remap.readthedocs.io/en/latest/
Project-URL: Repository, https://github.com/nhok0169/Anime-Game-Remap
Classifier: Programming Language :: Python :: 3
Classifier: License :: OSI Approved :: MIT License
Classifier: Operating System :: OS Independent
Requires-Python: >=3.6
License-File: LICENSE
Requires-Dist: FixRaidenBoss2==4.6.2
Dynamic: license-file
